pylmeasure/__init__.py
pylmeasure/LMLinux32/LMv5.0_ReleaseNotes_02042013.doc
pylmeasure/LMLinux32/Lm.jar
pylmeasure/LMLinux32/lmeasure
pylmeasure/LMLinux64/LMv5.0_ReleaseNotes_02042013.doc
pylmeasure/LMLinux64/Lm.jar
pylmeasure/LMLinux64/Lmin.txt
pylmeasure/LMLinux64/Lmout.txt
pylmeasure/LMLinux64/err.txt
pylmeasure/LMLinux64/lmeasure
pylmeasure/LMLinux64/run_LMeasure
pylmeasure/LMMac/LM.jar
pylmeasure/LMMac/LM6.0vReleaseNotes_02102011.docx
pylmeasure/LMMac/Lm.jar
pylmeasure/LMMac/lmeasure
pylmeasure/LMWin/LMv5.0_ReleaseNotes_02042013.doc
pylmeasure/LMWin/Lm.exe
pylmeasure/LMWin/Lm.jar
pylmeasure/util/__init__.py
pylmeasure/util/morphometricMeasurements.py
pylmeasure-0.2.0.dist-info/LICENSE
pylmeasure-0.2.0.dist-info/METADATA
pylmeasure-0.2.0.dist-info/WHEEL
pylmeasure-0.2.0.dist-info/top_level.txt
pylmeasure-0.2.0.dist-info/RECORD
