Metadata-Version: 2.1
Name: pylmeasure
Version: 0.2.0
Summary: A Python wrapper for L-Measure
Home-page: https://github.com/justasb/pylmeasure
Author: Ajayrama Kumaraswamy, Justas Birgiolas
Author-email: justas@asu.edu
License: UNKNOWN
Platform: UNKNOWN
Classifier: Programming Language :: Python :: 3
Classifier: License :: OSI Approved :: Apache Software License
Classifier: Operating System :: OS Independent
